qadence_measurement/__init__.py
qadence_measurement/calibration.py
qadence_measurement/manager.py
qadence_measurement/protocol.py
qadence_measurement/robust_shadow.py
qadence_measurement/shadow.py
qadence_measurement/tomography.py
qadence_measurement/utils/__init__.py
qadence_measurement/utils/data_acquisition.py
qadence_measurement/utils/post_processing.py
qadence_measurement/utils/types.py
qadence_measurement/utils/unitaries.py
qadence_measurement/utils/utils_tomography.py
qadence_measurement/utils/utils_trace.py
qadence_measurement-1.0.1.dist-info/METADATA
qadence_measurement-1.0.1.dist-info/WHEEL
qadence_measurement-1.0.1.dist-info/licenses/LICENSE
qadence_measurement-1.0.1.dist-info/RECORD
