Metadata-Version: 2.4
Name: qadence-measurement
Version: 1.0.1
Summary: Python package that provides measurement post-processing for Qadence.
Author-email: Mario Dagrada <mario.dagrada@pasqal.com>, Roland Guichard <roland.guichard@pasqal.com>, Raja Selvarajan <raja.selvarajan@pasqal.com>, Gergana Velikova <gergana.velikova@pasqal.com>, Charles Moussa <charles.moussa@pasqal.com>, Sungwoo Ahn <sungwoo.ahn@pasqal.com>
License: Apache 2.0
License-File: LICENSE
Keywords: quantum
Classifier: License :: OSI Approved :: Apache Software License
Classifier: Programming Language :: Python
Classifier: Programming Language :: Python :: 3.9
Classifier: Programming Language :: Python :: 3.10
Classifier: Programming Language :: Python :: 3.11
Classifier: Programming Language :: Python :: 3.12
Classifier: Programming Language :: Python :: 3.13
Classifier: Programming Language :: Python :: Implementation :: CPython
Classifier: Programming Language :: Python :: Implementation :: PyPy
Requires-Python: <3.14,>=3.9
Requires-Dist: qadence-commons
Requires-Dist: qadence[horqrux,pulser]
Requires-Dist: torch
